Bulk_cert_generator/Cert_gen.py
Bulk_cert_generator/__init__.py
Bulk_cert_generator/test.py
Bulk_cert_generator-1.0.1.dist-info/LICENSE.txt
Bulk_cert_generator-1.0.1.dist-info/METADATA
Bulk_cert_generator-1.0.1.dist-info/WHEEL
Bulk_cert_generator-1.0.1.dist-info/top_level.txt
Bulk_cert_generator-1.0.1.dist-info/RECORD
